mcp_agentskills/__init__.py
mcp_agentskills/main.py
mcp_agentskills/config/__init__.py
mcp_agentskills/config/config_parser.py
mcp_agentskills/config/default.yaml
mcp_agentskills/core/__init__.py
mcp_agentskills/core/tools/__init__.py
mcp_agentskills/core/tools/load_skill_metadata_op.py
mcp_agentskills/core/tools/load_skill_op.py
mcp_agentskills/core/tools/read_reference_file_op.py
mcp_agentskills/core/tools/run_shell_command_op.py
mcp_agentskills/core/tools/run_shell_command_prompt.yaml
mcp_agentskills/core/utils/service_runner.py
mcp_agentskills-0.1.2.dist-info/licenses/LICENSE
mcp_agentskills-0.1.2.dist-info/METADATA
mcp_agentskills-0.1.2.dist-info/WHEEL
mcp_agentskills-0.1.2.dist-info/entry_points.txt
mcp_agentskills-0.1.2.dist-info/top_level.txt
mcp_agentskills-0.1.2.dist-info/RECORD
