Metadata-Version: 2.4
Name: mcp-agentskills
Version: 0.1.2
Summary: An MCP server for bringing Anthropic's Agent Skills to any MCP-compatible agent.
Author-email: "jinli.yl" <jinli.yl@alibaba-inc.com>, "caozouying.czy" <caozouying.czy@alibaba-inc.com>
License:                                  Apache License
Project-URL: Homepage, https://github.com/zouyingcao/agentskills-mcp
Project-URL: Documentation, https://github.com/zouyingcao/agentskills-mcp/README.md
Project-URL: Repository, https://github.com/zouyingcao/agentskills-mcp
Keywords: llm,agent,skills,claude-skills,anthropic-agent-skills,mcp,model-context-protocol,flowllm,progressive-disclosure
Classifier: Development Status :: 4 - Beta
Classifier: Intended Audience :: Developers
Classifier: Intended Audience :: Science/Research
Classifier: License :: OSI Approved :: Apache Software License
Classifier: Operating System :: OS Independent
Classifier: Programming Language :: Python :: 3
Classifier: Programming Language :: Python :: 3.10
Classifier: Topic :: Scientific/Engineering :: Artificial Intelligence
Classifier: Topic :: Software Development :: Libraries :: Python Modules
Classifier: Topic :: Software Development :: Libraries :: Application Frameworks
Classifier: Typing :: Typed
Requires-Python: >=3.10
License-File: LICENSE
Requires-Dist: flowllm>=0.2.0.7
Requires-Dist: pipreqs
Provides-Extra: dev
Requires-Dist: pytest>=8.4.2; extra == "dev"
Requires-Dist: pytest_asyncio>=1.2.0; extra == "dev"
Requires-Dist: pre-commit; extra == "dev"
Requires-Dist: mkdocs-shadcn; extra == "dev"
Dynamic: license-file
